HW3/Problem3/Hex27Seg.v
// Michael Pate
// Professor Chao Jiang
// EE 4490 HDL Design
// Homework 3 - September 23, 2021
// Hex27Seg.v

module Hex27Seg(Leds, HexVal);
    output [0:6] Leds;
    input [3:0] HexVal;
    reg [0:6] Leds;

    always @(HexVal)
    begin
        case (HexVal)
            4'b0000: Leds = 7'b1111110;
            4'b0001: Leds = 7'b0110000;
            4'b0010: Leds = 7'b1101101;
            4'b0011: Leds = 7'b1111001;
            4'b0100: Leds = 7'b0110011;
            4'b0101: Leds = 7'b1011011;
            4'b0110: Leds = 7'b1011111;
            4'b0111: Leds = 7'b1110000;
            4'b1000: Leds = 7'b1111111;
            4'b1001: Leds = 7'b1111011;
            4'b1010: Leds = 7'b1110111;
            4'b1011: Leds = 7'b0011111;
            4'b1100: Leds = 7'b1001110;
            4'b1101: Leds = 7'b0111101;
            4'b1110: Leds = 7'b1001111;
            4'b1111: Leds = 7'b1000111;
        endcase
    end


endmodule

HW3/Problem3/tb_Hex27Seg.v
// Michael Pate
// Professor Chao Jiang
// EE 4490 HDL Design
// Homework 3 - September 23, 2021
// tb_Hex27Seg.v

`timescale 10ns/10ps
module tb_Hex27Seg;

    wire [0:6] t_Leds;
    reg [3:0] t_HexVal;

    initial begin $dumpfile("tb_Hex27Seg.vcd"); $dumpvars(0, tb_Hex27Seg); end

    Hex27Seg uut(t_Leds, t_HexVal);

    initial t_HexVal = 4'b0;

    initial
    fork
        #00      t_HexVal = 4'b0;
        #10      t_HexVal = 4'h1;
        #20      t_HexVal = 4'h2;
        #30      t_HexVal = 4'h3;
        #40      t_HexVal = 4'h4;
        #50      t_HexVal = 4'h5;
        #60      t_HexVal = 4'h6;
        #70      t_HexVal = 4'h7;
        #80      t_HexVal = 4'h8;
        #90      t_HexVal = 4'h9;
        #100     t_HexVal = 4'hA;
        #110     t_HexVal = 4'hB;
        #120     t_HexVal = 4'hC;
        #130     t_HexVal = 4'hD;
        #140     t_HexVal = 4'hE;
        #150     t_HexVal = 4'hF;
        #160     $finish;
    join

endmodule

HW3/Problem3/tb_Hex27Seg.vcd
$date
	Thu Sep 23 15:00:49 2021
$end
$version
	Icarus Verilog
$end
$timescale
	10ps
$end
$scope module tb_Hex27Seg $end
$var wire 7 ! t_Leds [0:6] $end
$var reg 4 " t_HexVal [3:0] $end
$scope module uut $end
$var wire 4 # HexVal [3:0] $end
$var reg 7 $ Leds [0:6] $end
$upscope $end
$upscope $end
$enddefinitions $end
#0
$dumpvars
b1111110 $
b0 #
b0 "
b1111110 !
$end
#10000
b110000 !
b110000 $
b1 "
b1 #
#20000
b1101101 !
b1101101 $
b10 "
b10 #
#30000
b1111001 !
b1111001 $
b11 "
b11 #
#40000
b110011 !
b110011 $
b100 "
b100 #
#50000
b1011011 !
b1011011 $
b101 "
b101 #
#60000
b1011111 !
b1011111 $
b110 "
b110 #
#70000
b1110000 !
b1110000 $
b111 "
b111 #
#80000
b1111111 !
b1111111 $
b1000 "
b1000 #
#90000
b1111011 !
b1111011 $
b1001 "
b1001 #
#100000
b1110111 !
b1110111 $
b1010 "
b1010 #
#110000
b11111 !
b11111 $
b1011 "
b1011 #
#120000
b1001110 !
b1001110 $
b1100 "
b1100 #
#130000
b111101 !
b111101 $
b1101 "
b1101 #
#140000
b1001111 !
b1001111 $
b1110 "
b1110 #
#150000
b1000111 !
b1000111 $
b1111 "
b1111 #
