Project1Michael/TableTennis/TableTennis.srcs/sources_1/imports/Project1Michael/gameSM.v
/**
	Michael Pate and Ean Hughes
	Professor Jiang
	HDL Digital Design
	UWYO EE 4490
	October 15, 2021
	gameSM.v
**/

module gameSM(field,p1score,p2score,clk,rst,ready,paddle1,paddle2, serve);
	input clk, rst, ready;
	input paddle1, paddle2, serve;
	
	output [4:0] field;
	output reg p1score, p2score;
	
	reg dir = 1;
	
	reg [4:0] S, nS;
	parameter [4:0] S_idle=5'b00000, S_1=5'b10000, S_2=5'b01000, S_3=5'b00100, S_4=5'b00010, S_5=5'b00001;
	assign field = S;
	
	// Handle reset
	always @(negedge rst)
	begin
		if (rst == 0)
			begin
				S <= S_idle;
				nS<= S_idle;
				p1score <= 0;
				p2score <= 0;
			end
	end	
	
	// Change states and handle moore outputs
	always @(posedge clk)
	begin
		case(S)
		S_idle:	begin
					//if (serve) nS <= dir ? S_4 : S_2;
					p1score <= 0;
					p2score <= 0;
					if (serve) nS <= S_3;
					else nS <= S_idle;
				end
		
		S_1:	begin 
					if (paddle1)
					begin
						dir <= 1;
						nS <= S_2;
					end
					else
					begin
						p2score <= 1;
						p1score <= 0;
						nS <= S_idle;
					end
				end
				
		S_2:	begin
					nS <= dir ? S_3 : S_1;
					p1score <= 0;
					p2score <= 0;
				end
				
		S_3:	begin
					nS <= dir ? S_4 : S_2;
					p1score <= 0;
					p2score <= 0;
				end
				
		S_4:	begin
					nS <= dir ? S_5 : S_3;
					p1score <= 0;
					p2score <= 0;
				end
				
		S_5:	begin 
					if (paddle2)
					begin
						dir <= 0;
						nS <= S_4;
					end
					else
					begin
						p2score <= 0;
						p1score <= 1;
						nS <= S_idle;
					end
				end	
		endcase
	end
	
	always @(posedge clk)
	begin
		if (ready == 1) S <= nS;
		else S <= S;
	end

endmodule

Project1Michael/TableTennis/TableTennis.srcs/sources_1/imports/Project1Michael/tb_gameSM.v
`timescale 1ns/1ns
module tb_gameSM();
	reg t_clk, t_rst;
	reg t_paddle1, t_paddle2, t_serve;
	reg t_ready;
	
	wire [4:0] t_field;
	wire t_score1, t_score2;
	
	gameSM uut(t_field, t_score1, t_score2, t_clk, t_rst, t_ready, t_paddle1, t_paddle2, t_serve);
	
	initial
	begin
		$dumpfile("tb_gameSM.vcd");
		$dumpvars(0, tb_gameSM);
	end
	
	always #5 t_clk = !t_clk;
	
	initial
	begin
		t_rst = 1;
		t_clk = 0;
		t_paddle1 = 1;
		t_paddle2 = 1;
		t_serve = 0;
		t_ready = 1;
	end
	
	initial
	begin
		#10	t_rst = 0;
		#10 t_serve = 1;
		#30 t_serve = 0;
		#100 t_paddle1 = 0;
		#120	t_serve = 1;
		#140	t_serve = 0;
		#240	$finish;
	end
	
endmodule

Project1Michael/TableTennis/TableTennis.srcs/sources_1/imports/Project1Michael/tb_gameSM.vcd
$date
	Mon Oct 18 07:30:44 2021
$end
$version
	Icarus Verilog
$end
$timescale
	1ns
$end
$scope module tb_gameSM $end
$var wire 1 ! t_score2 $end
$var wire 1 " t_score1 $end
$var wire 5 # t_field [4:0] $end
$var reg 1 $ t_clk $end
$var reg 1 % t_paddle1 $end
$var reg 1 & t_paddle2 $end
$var reg 1 ' t_ready $end
$var reg 1 ( t_rst $end
$var reg 1 ) t_serve $end
$scope module uut $end
$var wire 1 $ clk $end
$var wire 5 * field [4:0] $end
$var wire 1 % paddle1 $end
$var wire 1 & paddle2 $end
$var wire 1 ' ready $end
$var wire 1 ( rst $end
$var wire 1 ) serve $end
$var reg 5 + S [4:0] $end
$var reg 1 , dir $end
$var reg 5 - nS [4:0] $end
$var reg 1 " p1score $end
$var reg 1 ! p2score $end
$upscope $end
$upscope $end
$enddefinitions $end
#0
$dumpvars
bx -
1,
bx +
bx *
0)
1(
1'
1&
1%
0$
bx #
x"
x!
$end
#5
1$
#10
0!
0"
b0 -
b0 #
b0 *
b0 +
0$
0(
#15
1$
#20
0$
1)
#25
b100 -
1$
#30
0$
#35
b100 #
b100 *
b100 +
1$
#40
0$
#45
b10 -
1$
#50
0$
0)
#55
b10 #
b10 *
b10 +
1$
#60
0$
#65
b1 -
1$
#70
0$
#75
b1 #
b1 *
b1 +
1$
#80
0$
#85
b10 -
0,
1$
#90
0$
#95
b10 #
b10 *
b10 +
1$
#100
0$
#105
b100 -
1$
#110
0$
#115
b100 #
b100 *
b100 +
1$
#120
0$
#125
b1000 -
1$
#130
0$
#135
b1000 #
b1000 *
b1000 +
1$
#140
0$
#145
b10000 -
1$
#150
0$
0%
#155
b10000 #
b10000 *
b10000 +
1$
#160
0$
#165
b0 -
1!
1$
#170
0$
#175
b0 #
b0 *
b0 +
1$
#180
0$
#185
0!
1$
#190
0$
#195
1$
#200
0$
#205
1$
#210
0$
#215
1$
#220
0$
#225
1$
#230
0$
#235
1$
#240
0$
#245
1$
#250
0$
#255
1$
#260
0$
#265
1$
#270
0$
1)
#275
b100 -
1$
#280
0$
#285
b100 #
b100 *
b100 +
1$
#290
0$
#295
b1000 -
1$
#300
0$
#305
b1000 #
b1000 *
b1000 +
1$
#310
0$
#315
b10000 -
1$
#320
0$
#325
b10000 #
b10000 *
b10000 +
1$
#330
0$
#335
b0 -
1!
1$
#340
0$
#345
b0 #
b0 *
b0 +
1$
#350
0$
#355
b100 -
0!
1$
#360
0$
#365
b100 #
b100 *
b100 +
1$
#370
0$
#375
b1000 -
1$
#380
0$
#385
b1000 #
b1000 *
b1000 +
1$
#390
0$
#395
b10000 -
1$
#400
0$
#405
b10000 #
b10000 *
b10000 +
1$
#410
0$
0)
#415
b0 -
1!
1$
#420
0$
#425
b0 #
b0 *
b0 +
1$
#430
0$
#435
0!
1$
