Project1Michael/TableTennis/TableTennis.srcs/sources_1/imports/Project1Michael/ClockDivider.v
module ClockDivider(in, out, rst);
    input in, rst;
    output out;

    reg [31:0] currentCount;

    assign out = currentCount[5];

    always @(posedge in, negedge rst)
    begin
        if (rst == 0) begin currentCount <= 0;end
        else currentCount <= currentCount + 1'b1;
    end

endmodule

Project1Michael/TableTennis/TableTennis.srcs/sources_1/imports/Project1Michael/LEDPatternGenerator.v
module LEDPatternGenerator(colorOutput, fieldInput);
    input [4:0] fieldInput;
    output reg [119:0] colorOutput;

    always @(fieldInput)
    begin
        case(fieldInput)
            5'b10000:   colorOutput = 120'h00FF00101010101010101010101010;
            5'b01000:   colorOutput = 120'h10101000FF00101010101010101010;
            5'b00100:   colorOutput = 120'h10101000FF00101010101010101010;
            5'b00010:   colorOutput = 120'h10101010101010101000FF00101010;
            5'b00001:   colorOutput = 120'h10101010101010101010101000FF00;
            default:    colorOutput = 120'h0F0F0F0F0F0F0F0F0F0F0F0F0F0F0F;
        endcase
    end

endmodule

// 00FF00
// 101010

Project1Michael/TableTennis/TableTennis.srcs/sources_1/imports/Project1Michael/NZRbitGEN.v
// NZRbitGEN.v
// Generate NZR line code timing for WS2812B GRB LED Module,
// using a Digilent BASYS3 prototyping board with a
// Xilinx Artix-7 FPGA clocked at 100 MHz.
//
// This module must receive input qmode which specifies
// the current NZR  line code to be produced (for a "0", "1", RESET).
// The value of qmode should be held constant until
// the Moore output bdone is asserted.  A new qmode should
// then be supplied within 1/100M = 10 ns to begin the generation
// of the next line code.
//
// Adapted from earlier code by Jerry C. Hamann
// Modified for new production WB2812B with RESET > 280 us
//  qmode must supply at least 219 bit times of 1.28 us 
//   of state 10 to meet the new reset time of > 280 us
// EE 4490 
//
module NZRbitGEN(bout, bdone, qmode, startcoding, clk, reset);
  output  bout, bdone;  // bout  -- NZR signal
                          // bdone -- line code generation completed
  input   [1:0] qmode;  // Mode for generation:
                          // 2'b00 Produce a "0"
                          // 2'b01 Produce a "1"
                          // 2'b10 Solid low output (for resets)
                          // 2'b11 Solid high output (not used in WB2812B)
  input   startcoding;  // Like reset, drives counter to zero to synchronize code generation
  input   clk, reset;   // synchronous, 100 MHz assumed
  reg     bout;          
  reg     [6:0] bcount; // 0-127 count for generating NZR timing of a bit
                          // Note:  128*(1/100MHz) = 1.28 us (close enough to 1.25 us)

  // Implement state memory and next state for synchronous bcounter for bit time
  always @(posedge clk)
  // Depends on 7'h7F->7'h00 rollover at 1.28 us
  begin
    if((reset==0) || startcoding)
      bcount <= 0;
    else
      bcount <= bcount+1; 
   end

  always @(qmode or bcount) // bout produced based on qmode
  begin
    // 36*(1/(100 MHz)) = 0.36 us = 28% of 1.28 us
    // 92*(1/(100 MHz)) = 0.92 us = 72% of 1.28 us
    case(qmode)         
      2'b00:  bout = (bcount < 36) ? 1 : 0 ; // "0" in 1.28 us
      2'b01:  bout = (bcount < 92) ? 1 : 0 ; // "1" in 1.28 us
      2'b10:  bout = 0; // Produces "RESET" output, stays low
      2'b11:  bout = 1; // Reserved for future use
      default: bout = 0;
    endcase
  end

  assign bdone = (bcount == 127);  // Marks end of bit period
endmodule

Project1Michael/TableTennis/TableTennis.srcs/sources_1/imports/Project1Michael/BitCounter.v
// BitCounter.v
// Just a simple 8-bit synchronous counter
// Main inputs and outputs connect to GRBStateMachine
// Value of output Count keeps track of how many bits have been sent
// This implies a max of 10 LED modules could be used (240 bits)
// For longer LED strips, increase the bit width of the counter

module BitCounter(Count,ClearCounter,IncCounter,clk,reset);
  output  [7:0] Count;
  input   ClearCounter, IncCounter;
  input   clk, reset;

  reg [7:0] Count, nCount;

  always @(posedge clk)
    if(reset==0) Count <= 0;
    else Count <= nCount;

  always @(reset, Count, ClearCounter, IncCounter)
    if((reset==0) || ClearCounter)
      nCount = 0;
    else if(IncCounter)
      nCount = Count+1;
    else
      nCount = Count;
endmodule

Project1Michael/TableTennis/TableTennis.srcs/sources_1/imports/Project1Michael/ShiftRegister.v
// ShiftRegister.v
// determines the 24-bit control word for an LED module
// shifts it out one bit at a time
// keeps sending the same 24 bits, so same color to all modules

module ShiftRegister(CurrentBit,ParallelDataIn,LoadRegister,RotateRegisterLeft,clk,reset);
  output CurrentBit;
  input  [119:0] ParallelDataIn;
  input  LoadRegister, RotateRegisterLeft;
  input  clk, reset;

  parameter DEFAULTREG=120'h0F0F0F0F0F0F0F0F0F0F0F0F0F0F0F;  // white, half brightness

  reg [119:0]  TheReg, nTheReg;  // 24 bits for GRB control

  always @(posedge clk)
    if(reset==0) TheReg <= DEFAULTREG;
    else  TheReg <= nTheReg;
      
    // ParallelDataInitches set the upper 4 bits of the GRB control bytes
  always @(TheReg, LoadRegister, RotateRegisterLeft, ParallelDataIn)
    if(LoadRegister)
      nTheReg = ParallelDataIn;
    else if(RotateRegisterLeft)
      nTheReg = {TheReg[118:0],TheReg[119]};
    else
      nTheReg = TheReg;

  assign  CurrentBit = TheReg[119];
endmodule

Project1Michael/TableTennis/TableTennis.srcs/sources_1/imports/Project1Michael/GRBStateMachine.v
// GRBStateMachine.v
// Output qmode tells the NZRbitGEN module whether to send a 0, 1, RESET
// Updated to support new WS2812B reset code of > 280 us
// bdone ticks every bit period (1.28 us), RESET is > 280 us, use 281000 clks = 281 us

module GRBStateMachine(qmode,Done,LoadGRBPattern,ShiftPattern,StartCoding,
          ClrCounter,IncCounter,ShipGRB,theBit,bdone,Count,NumLEDs,clk,reset,allDone);
	output	[1:0]	qmode;
	output	allDone, Done, LoadGRBPattern, ShiftPattern, StartCoding, ClrCounter, IncCounter;
	input		ShipGRB, theBit, bdone;
	input   [7:0]	Count;
	input   [3:1] NumLEDs;
	input		clk, reset;
  
  reg	     	S, nS;
	parameter	SSHIPRET=1'b0, SSHIPGRB=1'b1;

  reg      [7:0]   COMPAREVAL;
  reg      [14:0]  rCount;  // counter for RESET time

	always @(posedge clk)
		if(reset==0)
			S <= SSHIPRET;
		else
			S <= nS;

	always @(S, ShipGRB, bdone, Count)
		case(S)
			SSHIPRET:  nS = ShipGRB ? SSHIPGRB : SSHIPRET;
			SSHIPGRB:  nS = (bdone && (Count==COMPAREVAL)) ? SSHIPRET : SSHIPGRB;
			default:   nS = SSHIPRET;
		endcase

	assign LoadGRBPattern = (S==SSHIPRET)&&ShipGRB;
	assign ClrCounter     = (S==SSHIPRET)&&ShipGRB;
	assign StartCoding    = (S==SSHIPRET)&&ShipGRB;
	assign ShiftPattern   = (S==SSHIPGRB)&&bdone;
	assign IncCounter     = (S==SSHIPGRB)&&bdone;
	assign qmode          = (S==SSHIPRET) ? 2'b10 : {1'b0,theBit};
	assign Done           = (S==SSHIPGRB)&&bdone&&(Count==COMPAREVAL);
	assign allDone        = (S==SSHIPRET)&&(rCount==15'd28100); // 281 us

//	assign allDone  = (S==SSHIPRET)&&(rCount==15'd3000); // for testing only  

  always @(NumLEDs)
    case(NumLEDs)  // how many LED modules?
      3'b001:  COMPAREVAL = 23;  // 1*24 = 24 bits
      3'b010:  COMPAREVAL = 47;  // 2*24 = 48 bits
      3'b011:  COMPAREVAL = 71;  // 3*24 = 72 bits
			3'b100:  COMPAREVAL = 95;  // 4*24 = 96 bits
      3'b101:  COMPAREVAL = 119; // 5*24 = 120 bits
      default: COMPAREVAL = 23;  // default to one module
    endcase

  always @(posedge clk)
  // counts time for RESET, 10 ns per tick
  begin
    if((reset==0) || Done)  // Done sending bits, start RESET
      rCount <= 0;
    else if (S==SSHIPRET)
      rCount <= rCount+1; 
    else rCount <= rCount;
  end
 
endmodule

Project1Michael/TableTennis/TableTennis.srcs/sources_1/imports/Project1Michael/SSStateMachine.v
// SSStateMachine.v
// Allows user to reset system with SW0 or say "Go" with center button
//   as defined in xdc file
// Input Done comes from GRBStateMachine when it's sent all the bits
//   but not RESET yet 
// Input allDone comes from GRBStateMachine when it's sent the RESET code
// Incorporates debouncing delay for the button
// Output shipGRB tells GRBStateMachine to keep sending data bits 
// Updated to support new WS2812B reset code of > 280 us

module SSStateMachine(shipGRB,Done,Go,clk,reset,allDone,Ready2Go);
	output	shipGRB, Ready2Go;
	input	allDone, Done, Go;
	input	clk, reset;

	reg [1:0]	S, nS;
	parameter	SWAIT=2'b00, SSHIP=2'b01, SRET=2'b10, SDBOUNCE=2'b11;

	always @(posedge clk)
		if(reset==0)
			S <= SWAIT;
		else
			S <= nS;

	always @(S, Go, Done, allDone)
		case(S)
			SWAIT: 		nS = Go      ? SSHIP    : SWAIT;
			SSHIP:		nS = Done    ? SRET     : SSHIP;
      SRET:		  nS = allDone ? SDBOUNCE : SRET;
			SDBOUNCE:	nS = Go      ? SDBOUNCE : SWAIT;
			default:	nS = SWAIT;
		endcase

  assign Ready2Go = (S==SWAIT);  // okay to press Go
	assign shipGRB  = (S==SSHIP);  // send data bits
endmodule

Project1Michael/TableTennis/TableTennis.srcs/sources_1/imports/Project1Michael/SimpleSend.v
// SimpleSend.v
// top-level module for WS2812B LED strip
// VERY basic design, sends same color to all modules
// Updated to support new WS2812B reset code of > 280 us

module SimpleSend(dataOut,ColorDataIn,Go,clk,reset,Ready2Go);
	output	dataOut, Ready2Go;
	input   [119:0] ColorDataIn;
	input	Go, clk, reset;

	reg [2:0] NumLEDs = 3'd5;

	wire		shipGRB, Done, allDone;
	wire [1:0]	qmode;
	wire		LoadGRBPattern, ShiftPattern, StartCoding, ClrCounter, IncCounter, theBit, bdone;
	wire [7:0]	Count;

	SSStateMachine	sssm(shipGRB,Done,Go,clk,reset,allDone,Ready2Go);
	GRBStateMachine grbsm(qmode,Done,LoadGRBPattern,ShiftPattern,StartCoding,ClrCounter,IncCounter,
                              shipGRB,theBit,bdone,Count,NumLEDs,clk,reset,allDone);
	ShiftRegister   shftr(theBit,ColorDataIn,LoadGRBPattern,ShiftPattern,clk,reset);
	BitCounter	btcnt(Count,ClrCounter,IncCounter,clk,reset);
	NZRbitGEN	nzrgn(dataOut,bdone,qmode,StartCoding,clk,reset);
endmodule

Project1Michael/TableTennis/TableTennis.srcs/sources_1/imports/Project1Michael/gameSM.v
/**
	Michael Pate and Ean Hughes
	Professor Jiang
	HDL Digital Design
	UWYO EE 4490
	October 15, 2021
	gameSM.v
**/

module gameSM(field,p1score,p2score,clk,rst,ready,paddle1,paddle2, serve);
	input clk, rst, ready;
	input paddle1, paddle2, serve;
	
	output [4:0] field;
	output reg p1score, p2score;
	
	reg dir = 1;
	
	reg [4:0] S, nS;
	parameter [4:0] S_idle=5'b00000, S_1=5'b10000, S_2=5'b01000, S_3=5'b00100, S_4=5'b00010, S_5=5'b00001;
	assign field = S;
	
	// Handle reset
	always @(negedge rst)
	begin
		if (rst == 0)
			begin
				S <= S_idle;
				nS<= S_idle;
				p1score <= 0;
				p2score <= 0;
			end
	end	
	
	// Change states and handle moore outputs
	always @(posedge clk)
	begin
		case(S)
		S_idle:	begin
					//if (serve) nS <= dir ? S_4 : S_2;
					p1score <= 0;
					p2score <= 0;
					if (serve) nS <= S_3;
					else nS <= S_idle;
				end
		
		S_1:	begin 
					if (paddle1)
					begin
						dir <= 1;
						nS <= S_2;
					end
					else
					begin
						p2score <= 1;
						p1score <= 0;
						nS <= S_idle;
					end
				end
				
		S_2:	begin
					nS <= dir ? S_3 : S_1;
					p1score <= 0;
					p2score <= 0;
				end
				
		S_3:	begin
					nS <= dir ? S_4 : S_2;
					p1score <= 0;
					p2score <= 0;
				end
				
		S_4:	begin
					nS <= dir ? S_5 : S_3;
					p1score <= 0;
					p2score <= 0;
				end
				
		S_5:	begin 
					if (paddle2)
					begin
						dir <= 0;
						nS <= S_4;
					end
					else
					begin
						p2score <= 0;
						p1score <= 1;
						nS <= S_idle;
					end
				end	
		endcase
	end
	
	always @(posedge clk)
	begin
		if (ready == 1) S <= nS;
		else S <= S;
	end

endmodule

Project1Michael/TableTennis/TableTennis.srcs/sources_1/imports/Project1Michael/topLevel.v

/**
        The top level module needs to connect SimpleSend, the game SM, and score counters and an interface to the seven segment display.



**/

module topLevel(RGBSerialData, sevenSegmentDigit, sevenSegmentData, readyLED, clk, rstAL, paddle1, paddle2, serve);
    input clk, rstAL;
    input paddle1, paddle2, serve;
    output RGBSerialData;
    output [3:0] sevenSegmentDigit;
    output [6:0] sevenSegmentData;
    output readyLED;

    wire [4:0] currentField; 
    wire player1score, player2score;
    wire gameClk;
    wire [119:0] colorData;
    wire ReadyForNextState;
    wire rst;

    assign readyLED = ReadyForNextState;
    assign rst = !rstAL;
 
    gameSM MainGameSM(currentField, player1score, player2score,
        gameClk, rst, ReadyForNextState, paddle1, paddle2, serve);
 
    SimpleSend LEDController(RGBSerialData, colorData, gameClk, clk, rst, ReadyForNextState);

    // Need an adapter that takes currentField and generates 120 bits based off that.
    // Those 120 bits go to SimpleSend's ColorDataIn.
    // Which gets passed to a shift register for output.
    // Just need to tick SimpleSend's Go input using gameClk
    LEDPatternGenerator FieldStateAdapter(colorData, currentField);

    // Need to generate gameClk.
    ClockDivider gameClkGenerator(clk, gameClk, rst);

    // Need to add score counters and seven segment display

endmodule

Project1Michael/TableTennis/TableTennis.srcs/sources_1/imports/Project1Michael/tb_topLevel.v
`timescale 10ns/1ns
`include "gameSM.v"
`include "SimpleSend.v"
`include "LEDPatternGenerator.v"
`include "ClockDivider.v"
`include "SSStateMachine.v"
`include "GRBStateMachine.v"
`include "ShiftRegister.v"
`include "BitCounter.v"
`include "NZRBitGEN.v"
module tb_topLevel();
    reg t_clk, t_rst;
    reg t_pad1, t_pad2, t_serve;
    wire t_RGBSerialData;
    wire [3:0] t_anodeSelect;
    wire [6:0] t_sevenSegmentData;
    wire t_readyLED;

    topLevel uut(t_RGBSerialData, t_anodeSelect, t_sevenSegmentData,
        t_readyLED, t_clk, t_rst, t_pad1, t_pad2, t_serve);
    
    initial
	begin
		$dumpfile("tb_topLevel.vcd");
		$dumpvars(0, tb_topLevel);
	end

    always #1 t_clk = !t_clk;

    initial
    begin
        t_rst = 1;
        t_clk = 0;
        t_pad1 = 0;
        t_pad2 = 0;
        t_serve = 0;
    end

    initial
    begin
        #5 t_rst = 0;
        #30 t_serve = 1;
        #60 t_serve = 0;
        #4000 $finish;
    end

endmodule

Project1Michael/TableTennis/TableTennis.srcs/sources_1/imports/Project1Michael/tb_topLevel.vcd
$date
	Mon Oct 18 07:01:29 2021
$end
$version
	Icarus Verilog
$end
$timescale
	1ns
$end
$scope module tb_topLevel $end
$var wire 4 ! t_anodeSelect [3:0] $end
$var wire 7 " t_sevenSegmentData [6:0] $end
$var wire 1 # t_readyLED $end
$var wire 1 $ t_RGBSerialData $end
$var reg 1 % t_clk $end
$var reg 1 & t_pad1 $end
$var reg 1 ' t_pad2 $end
$var reg 1 ( t_rst $end
$var reg 1 ) t_serve $end
$scope module uut $end
$var wire 1 % clk $end
$var wire 1 & paddle1 $end
$var wire 1 ' paddle2 $end
$var wire 1 # readyLED $end
$var wire 1 ( rstAL $end
$var wire 1 ) serve $end
$var wire 7 * sevenSegmentData [6:0] $end
$var wire 4 + sevenSegmentDigit [3:0] $end
$var wire 1 , rst $end
$var wire 1 - player2score $end
$var wire 1 . player1score $end
$var wire 1 / gameClk $end
$var wire 5 0 currentField [4:0] $end
$var wire 120 1 colorData [119:0] $end
$var wire 1 2 ReadyForNextState $end
$var wire 1 $ RGBSerialData $end
$scope module FieldStateAdapter $end
$var wire 5 3 fieldInput [4:0] $end
$var reg 120 4 colorOutput [119:0] $end
$upscope $end
$scope module LEDController $end
$var wire 120 5 ColorDataIn [119:0] $end
$var wire 1 % clk $end
$var wire 1 , reset $end
$var wire 1 6 theBit $end
$var wire 1 7 shipGRB $end
$var wire 2 8 qmode [1:0] $end
$var wire 1 $ dataOut $end
$var wire 1 9 bdone $end
$var wire 1 : allDone $end
$var wire 1 ; StartCoding $end
$var wire 1 < ShiftPattern $end
$var wire 1 2 Ready2Go $end
$var wire 1 = LoadGRBPattern $end
$var wire 1 > IncCounter $end
$var wire 1 / Go $end
$var wire 1 ? Done $end
$var wire 8 @ Count [7:0] $end
$var wire 1 A ClrCounter $end
$var reg 3 B NumLEDs [2:0] $end
$scope module btcnt $end
$var wire 1 % clk $end
$var wire 1 , reset $end
$var wire 1 > IncCounter $end
$var wire 1 A ClearCounter $end
$var reg 8 C Count [7:0] $end
$var reg 8 D nCount [7:0] $end
$upscope $end
$scope module grbsm $end
$var wire 1 A ClrCounter $end
$var wire 8 E Count [7:0] $end
$var wire 1 ? Done $end
$var wire 1 > IncCounter $end
$var wire 1 = LoadGRBPattern $end
$var wire 3 F NumLEDs [3:1] $end
$var wire 1 < ShiftPattern $end
$var wire 1 ; StartCoding $end
$var wire 1 : allDone $end
$var wire 1 % clk $end
$var wire 1 , reset $end
$var wire 1 6 theBit $end
$var wire 2 G qmode [1:0] $end
$var wire 1 9 bdone $end
$var wire 1 7 ShipGRB $end
$var reg 8 H COMPAREVAL [7:0] $end
$var reg 1 I S $end
$var reg 1 J nS $end
$var reg 15 K rCount [14:0] $end
$upscope $end
$scope module nzrgn $end
$var wire 1 % clk $end
$var wire 2 L qmode [1:0] $end
$var wire 1 , reset $end
$var wire 1 ; startcoding $end
$var wire 1 9 bdone $end
$var reg 7 M bcount [6:0] $end
$var reg 1 $ bout $end
$upscope $end
$scope module shftr $end
$var wire 1 = LoadRegister $end
$var wire 120 N ParallelDataIn [119:0] $end
$var wire 1 < RotateRegisterLeft $end
$var wire 1 % clk $end
$var wire 1 , reset $end
$var wire 1 6 CurrentBit $end
$var reg 120 O TheReg [119:0] $end
$var reg 120 P nTheReg [119:0] $end
$upscope $end
$scope module sssm $end
$var wire 1 ? Done $end
$var wire 1 : allDone $end
$var wire 1 % clk $end
$var wire 1 , reset $end
$var wire 1 7 shipGRB $end
$var wire 1 2 Ready2Go $end
$var wire 1 / Go $end
$var reg 2 Q S [1:0] $end
$var reg 2 R nS [1:0] $end
$upscope $end
$upscope $end
$scope module MainGameSM $end
$var wire 5 S field [4:0] $end
$var wire 1 & paddle1 $end
$var wire 1 ' paddle2 $end
$var wire 1 2 ready $end
$var wire 1 , rst $end
$var wire 1 ) serve $end
$var wire 1 / clk $end
$var reg 5 T S [4:0] $end
$var reg 1 U dir $end
$var reg 5 V nS [4:0] $end
$var reg 1 . p1score $end
$var reg 1 - p2score $end
$upscope $end
$scope module gameClkGenerator $end
$var wire 1 % in $end
$var wire 1 , rst $end
$var wire 1 / out $end
$var reg 32 W currentCount [31:0] $end
$upscope $end
$upscope $end
$upscope $end
$enddefinitions $end
#0
$dumpvars
b0 W
b0 V
1U
b0 T
b0 S
b0 R
bx Q
bx P
bx O
b11110000111100001111000011110000111100001111000011110000111100001111000011110000111100001111000011110000111100001111 N
bx M
bx L
bx K
xJ
xI
b1110111 H
bx G
b101 F
bx E
bx D
bx C
b101 B
xA
bx @
x?
x>
x=
x<
x;
x:
x9
bx 8
x7
x6
b11110000111100001111000011110000111100001111000011110000111100001111000011110000111100001111000011110000111100001111 5
b11110000111100001111000011110000111100001111000011110000111100001111000011110000111100001111000011110000111100001111 4
b0 3
x2
b11110000111100001111000011110000111100001111000011110000111100001111000011110000111100001111000011110000111100001111 1
b0 0
0/
0.
0-
0,
bz +
bz *
0)
1(
0'
0&
0%
0$
x#
bz "
bz !
$end
#10
0;
0A
0=
0J
1#
12
07
b0 Q
1%
#20
0%
#30
0?
b10 8
b10 G
b10 L
0>
0<
0I
1%
#40
0%
#50
0:
b11110000111100001111000011110000111100001111000011110000111100001111000011110000111100001111000011110000111100001111 P
06
b0 K
b11110000111100001111000011110000111100001111000011110000111100001111000011110000111100001111000011110000111100001111 O
b0 @
b0 C
b0 E
09
b0 M
b1 W
b0 D
1%
1,
0(
#60
0%
#70
b10 W
1%
#80
0%
#90
b11 W
1%
#100
0%
#110
b100 W
1%
#120
0%
#130
b101 W
1%
#140
0%
#150
b110 W
1%
#160
0%
#170
b111 W
1%
#180
0%
#190
b1000 W
1%
#200
0%
#210
b1001 W
1%
#220
0%
#230
b1010 W
1%
#240
0%
#250
b1011 W
1%
#260
0%
#270
b1100 W
1%
#280
0%
#290
b1101 W
1%
#300
0%
#310
b1110 W
1%
#320
0%
#330
b1111 W
1%
#340
0%
#350
b10000 W
1%
1)
#360
0%
#370
b10001 W
1%
#380
0%
#390
b10010 W
1%
#400
0%
#410
b10011 W
1%
#420
0%
#430
b10100 W
1%
#440
0%
#450
b10101 W
1%
#460
0%
#470
b10110 W
1%
#480
0%
#490
b10111 W
1%
#500
0%
#510
b11000 W
1%
#520
0%
#530
b11001 W
1%
#540
0%
#550
b11010 W
1%
#560
0%
#570
b11011 W
1%
#580
0%
#590
b11100 W
1%
#600
0%
#610
b11101 W
1%
#620
0%
#630
b11110 W
1%
#640
0%
#650
b11111 W
1%
#660
0%
#670
b100 V
b1 R
1/
b100000 W
1%
#680
0%
#690
b100001 W
1%
#700
0%
#710
b100010 W
1%
#720
0%
#730
b100011 W
1%
#740
0%
#750
b100100 W
1%
#760
0%
#770
b100101 W
1%
#780
0%
#790
b100110 W
1%
#800
0%
#810
b100111 W
1%
#820
0%
#830
b101000 W
1%
#840
0%
#850
b101001 W
1%
#860
0%
#870
b101010 W
1%
#880
0%
#890
b101011 W
1%
#900
0%
#910
b101100 W
1%
#920
0%
#930
b101101 W
1%
#940
0%
#950
b101110 W
1%
0)
#960
0%
#970
b101111 W
1%
#980
0%
#990
b110000 W
1%
#1000
0%
#1010
b110001 W
1%
#1020
0%
#1030
b110010 W
1%
#1040
0%
#1050
b110011 W
1%
#1060
0%
#1070
b110100 W
1%
#1080
0%
#1090
b110101 W
1%
#1100
0%
#1110
b110110 W
1%
#1120
0%
#1130
b110111 W
1%
#1140
0%
#1150
b111000 W
1%
#1160
0%
#1170
b111001 W
1%
#1180
0%
#1190
b111010 W
1%
#1200
0%
#1210
b111011 W
1%
#1220
0%
#1230
b111100 W
1%
#1240
0%
#1250
b111101 W
1%
#1260
0%
#1270
b111110 W
1%
#1280
0%
#1290
b111111 W
1%
#1300
0%
#1310
b0 R
0/
b1000000 W
1%
#1320
0%
#1330
b1000001 W
1%
#1340
0%
#1350
b1000010 W
1%
#1360
0%
#1370
b1000011 W
1%
#1380
0%
#1390
b1000100 W
1%
#1400
0%
#1410
b1000101 W
1%
#1420
0%
#1430
b1000110 W
1%
#1440
0%
#1450
b1000111 W
1%
#1460
0%
#1470
b1001000 W
1%
#1480
0%
#1490
b1001001 W
1%
#1500
0%
#1510
b1001010 W
1%
#1520
0%
#1530
b1001011 W
1%
#1540
0%
#1550
b1001100 W
1%
#1560
0%
#1570
b1001101 W
1%
#1580
0%
#1590
b1001110 W
1%
#1600
0%
#1610
b1001111 W
1%
#1620
0%
#1630
b1010000 W
1%
#1640
0%
#1650
b1010001 W
1%
#1660
0%
#1670
b1010010 W
1%
#1680
0%
#1690
b1010011 W
1%
#1700
0%
#1710
b1010100 W
1%
#1720
0%
#1730
b1010101 W
1%
#1740
0%
#1750
b1010110 W
1%
#1760
0%
#1770
b1010111 W
1%
#1780
0%
#1790
b1011000 W
1%
#1800
0%
#1810
b1011001 W
1%
#1820
0%
#1830
b1011010 W
1%
#1840
0%
#1850
b1011011 W
1%
#1860
0%
#1870
b1011100 W
1%
#1880
0%
#1890
b1011101 W
1%
#1900
0%
#1910
b1011110 W
1%
#1920
0%
#1930
b1011111 W
1%
#1940
0%
#1950
b11110000111100001111000011110000111100001111000000001111111100000000000011110000111100001111000011110000111100001111 1
b11110000111100001111000011110000111100001111000000001111111100000000000011110000111100001111000011110000111100001111 4
b11110000111100001111000011110000111100001111000000001111111100000000000011110000111100001111000011110000111100001111 5
b11110000111100001111000011110000111100001111000000001111111100000000000011110000111100001111000011110000111100001111 N
b100 0
b100 3
b100 S
b100 T
b0 V
b1 R
1/
b1100000 W
1%
#1960
0%
#1970
b1100001 W
1%
#1980
0%
#1990
b1100010 W
1%
#2000
0%
#2010
b1100011 W
1%
#2020
0%
#2030
b1100100 W
1%
#2040
0%
#2050
b1100101 W
1%
#2060
0%
#2070
b1100110 W
1%
#2080
0%
#2090
b1100111 W
1%
#2100
0%
#2110
b1101000 W
1%
#2120
0%
#2130
b1101001 W
1%
#2140
0%
#2150
b1101010 W
1%
#2160
0%
#2170
b1101011 W
1%
#2180
0%
#2190
b1101100 W
1%
#2200
0%
#2210
b1101101 W
1%
#2220
0%
#2230
b1101110 W
1%
#2240
0%
#2250
b1101111 W
1%
#2260
0%
#2270
b1110000 W
1%
#2280
0%
#2290
b1110001 W
1%
#2300
0%
#2310
b1110010 W
1%
#2320
0%
#2330
b1110011 W
1%
#2340
0%
#2350
b1110100 W
1%
#2360
0%
#2370
b1110101 W
1%
#2380
0%
#2390
b1110110 W
1%
#2400
0%
#2410
b1110111 W
1%
#2420
0%
#2430
b1111000 W
1%
#2440
0%
#2450
b1111001 W
1%
#2460
0%
#2470
b1111010 W
1%
#2480
0%
#2490
b1111011 W
1%
#2500
0%
#2510
b1111100 W
1%
#2520
0%
#2530
b1111101 W
1%
#2540
0%
#2550
b1111110 W
1%
#2560
0%
#2570
b1111111 W
1%
#2580
0%
#2590
b0 R
0/
b10000000 W
1%
#2600
0%
#2610
b10000001 W
1%
#2620
0%
#2630
b10000010 W
1%
#2640
0%
#2650
b10000011 W
1%
#2660
0%
#2670
b10000100 W
1%
#2680
0%
#2690
b10000101 W
1%
#2700
0%
#2710
b10000110 W
1%
#2720
0%
#2730
b10000111 W
1%
#2740
0%
#2750
b10001000 W
1%
#2760
0%
#2770
b10001001 W
1%
#2780
0%
#2790
b10001010 W
1%
#2800
0%
#2810
b10001011 W
1%
#2820
0%
#2830
b10001100 W
1%
#2840
0%
#2850
b10001101 W
1%
#2860
0%
#2870
b10001110 W
1%
#2880
0%
#2890
b10001111 W
1%
#2900
0%
#2910
b10010000 W
1%
#2920
0%
#2930
b10010001 W
1%
#2940
0%
#2950
b10010010 W
1%
#2960
0%
#2970
b10010011 W
1%
#2980
0%
#2990
b10010100 W
1%
#3000
0%
#3010
b10010101 W
1%
#3020
0%
#3030
b10010110 W
1%
#3040
0%
#3050
b10010111 W
1%
#3060
0%
#3070
b10011000 W
1%
#3080
0%
#3090
b10011001 W
1%
#3100
0%
#3110
b10011010 W
1%
#3120
0%
#3130
b10011011 W
1%
#3140
0%
#3150
b10011100 W
1%
#3160
0%
#3170
b10011101 W
1%
#3180
0%
#3190
b10011110 W
1%
#3200
0%
#3210
b10011111 W
1%
#3220
0%
#3230
b11110000111100001111000011110000111100001111000011110000111100001111000011110000111100001111000011110000111100001111 1
b11110000111100001111000011110000111100001111000011110000111100001111000011110000111100001111000011110000111100001111 4
b11110000111100001111000011110000111100001111000011110000111100001111000011110000111100001111000011110000111100001111 5
b11110000111100001111000011110000111100001111000011110000111100001111000011110000111100001111000011110000111100001111 N
b10 V
b0 0
b0 3
b0 S
b0 T
b1 R
1/
b10100000 W
1%
#3240
0%
#3250
b10100001 W
1%
#3260
0%
#3270
b10100010 W
1%
#3280
0%
#3290
b10100011 W
1%
#3300
0%
#3310
b10100100 W
1%
#3320
0%
#3330
b10100101 W
1%
#3340
0%
#3350
b10100110 W
1%
#3360
0%
#3370
b10100111 W
1%
#3380
0%
#3390
b10101000 W
1%
#3400
0%
#3410
b10101001 W
1%
#3420
0%
#3430
b10101010 W
1%
#3440
0%
#3450
b10101011 W
1%
#3460
0%
#3470
b10101100 W
1%
#3480
0%
#3490
b10101101 W
1%
#3500
0%
#3510
b10101110 W
1%
#3520
0%
#3530
b10101111 W
1%
#3540
0%
#3550
b10110000 W
1%
#3560
0%
#3570
b10110001 W
1%
#3580
0%
#3590
b10110010 W
1%
#3600
0%
#3610
b10110011 W
1%
#3620
0%
#3630
b10110100 W
1%
#3640
0%
#3650
b10110101 W
1%
#3660
0%
#3670
b10110110 W
1%
#3680
0%
#3690
b10110111 W
1%
#3700
0%
#3710
b10111000 W
1%
#3720
0%
#3730
b10111001 W
1%
#3740
0%
#3750
b10111010 W
1%
#3760
0%
#3770
b10111011 W
1%
#3780
0%
#3790
b10111100 W
1%
#3800
0%
#3810
b10111101 W
1%
#3820
0%
#3830
b10111110 W
1%
#3840
0%
#3850
b10111111 W
1%
#3860
0%
#3870
b0 R
0/
b11000000 W
1%
#3880
0%
#3890
b11000001 W
1%
#3900
0%
#3910
b11000010 W
1%
#3920
0%
#3930
b11000011 W
1%
#3940
0%
#3950
b11000100 W
1%
#3960
0%
#3970
b11000101 W
1%
#3980
0%
#3990
b11000110 W
1%
#4000
0%
#4010
b11000111 W
1%
#4020
0%
#4030
b11001000 W
1%
#4040
0%
#4050
b11001001 W
1%
#4060
0%
#4070
b11001010 W
1%
#4080
0%
#4090
b11001011 W
1%
#4100
0%
#4110
b11001100 W
1%
#4120
0%
#4130
b11001101 W
1%
#4140
0%
#4150
b11001110 W
1%
#4160
0%
#4170
b11001111 W
1%
#4180
0%
#4190
b11010000 W
1%
#4200
0%
#4210
b11010001 W
1%
#4220
0%
#4230
b11010010 W
1%
#4240
0%
#4250
b11010011 W
1%
#4260
0%
#4270
b11010100 W
1%
#4280
0%
#4290
b11010101 W
1%
#4300
0%
#4310
b11010110 W
1%
#4320
0%
#4330
b11010111 W
1%
#4340
0%
#4350
b11011000 W
1%
#4360
0%
#4370
b11011001 W
1%
#4380
0%
#4390
b11011010 W
1%
#4400
0%
#4410
b11011011 W
1%
#4420
0%
#4430
b11011100 W
1%
#4440
0%
#4450
b11011101 W
1%
#4460
0%
#4470
b11011110 W
1%
#4480
0%
#4490
b11011111 W
1%
#4500
0%
