HW2/SSStateMachine.v
// Michael Pate
// Professor Chao Jiang
// EE 4490 HDL Design
// Homework 2 - September 13, 2021
// SSStateMachine.v

module SSStateMachine(shipGRB, Done, Go, clk, reset, allDone, Ready2Go);
    output reg shipGRB, Ready2Go;
    input allDone, Done, Go;
    input clk, reset;
    
    reg [1:0] S, nS;
    parameter SWAIT=2'b00, SSHIP=2'b01, SRET=2'b10, SDBOUNCE=2'b11;

    // Generate current state (Moore) outputs
    always @(S)
    begin
        case (S)
            SWAIT:      begin Ready2Go = 1; shipGRB = 0; end
            SSHIP:      begin Ready2Go = 0; shipGRB = 1; end
            SRET:       begin Ready2Go = 0; shipGRB = 0; end
            SDBOUNCE:   begin Ready2Go = 0; shipGRB = 0; end
        endcase
    end

    // Handle reset and state switching
    always @(posedge clk, posedge reset)
    begin
        if (reset == 1) S <= SWAIT;
        else S <= nS;
    end

    // Generate the next state
    always @(S, allDone, Done, Go)
    begin
        case (S)
            SWAIT:      if (Go) nS = SSHIP; else nS = SWAIT;
            SSHIP:      if (Done) nS = SRET; else nS = SSHIP;
            SRET:       if (allDone) nS = SDBOUNCE; else nS = SRET;
            SDBOUNCE:   if (Go) nS = SDBOUNCE; else nS = SWAIT;
        endcase
    end

endmodule

HW2/tb_SSStateMachine.v
// Michael Pate
// Professor Chao Jiang
// EE 4490 HDL Design
// Homework 2 - September 13, 2021
// tb_SSStateMachine.v
`timescale 10ns/100ps
module tb_SSStateMachine();

    wire t_shipGRB, t_Ready2Go;
    reg t_allDone, t_Done, t_Go, t_clk, t_reset;

    SSStateMachine uut(t_shipGRB, t_Done, t_Go, t_clk, t_reset, t_allDone, t_Ready2Go);

    // Setup capture device
    initial
    begin
        $dumpfile("tb_SSStateMachine.vcd");
        $dumpvars(0, tb_SSStateMachine);
    end

    // Clock generation and simulation timer
    initial begin t_clk = 0; forever #1 t_clk = ~t_clk; end

    // Initial conditions
    initial
    begin
        t_allDone = 0;
        t_Done = 0;
        t_Go = 0;
        t_reset = 1;
    end

    // Stimulus
    initial
    begin
        #0     begin t_allDone = 0; t_Done = 0; t_Go = 0; t_reset = 0; end
        #40     begin t_allDone = 0; t_Done = 0; t_Go = 1; t_reset = 0; end
        #10     begin t_allDone = 0; t_Done = 0; t_Go = 0; t_reset = 0; end
        #80     begin t_allDone = 0; t_Done = 1; t_Go = 0; t_reset = 0; end
        #10     begin t_allDone = 0; t_Done = 0; t_Go = 0; t_reset = 0; end
        #80     begin t_allDone = 0; t_Done = 0; t_Go = 1; t_reset = 0; end
        #10    begin t_allDone = 0; t_Done = 0; t_Go = 0; t_reset = 0; end
        #80     begin t_allDone = 1; t_Done = 0; t_Go = 0; t_reset = 0; end
        #10     begin t_allDone = 0; t_Done = 0; t_Go = 0; t_reset = 0; end
        #80     begin t_allDone = 0; t_Done = 0; t_Go = 1; t_reset = 0; end
        #80     begin t_allDone = 0; t_Done = 1; t_Go = 1; t_reset = 0; end
        #10     begin t_allDone = 0; t_Done = 0; t_Go = 1; t_reset = 0; end
        #80     begin t_allDone = 1; t_Done = 0; t_Go = 1; t_reset = 0; end
        #10     begin t_allDone = 0; t_Done = 0; t_Go = 1; t_reset = 0; end
        #80     begin t_allDone = 0; t_Done = 0; t_Go = 0; t_reset = 0; end
        #80 $finish;
    end   

endmodule

HW2/tb_SSStateMachine Pate.vcd
$date
	Mon Sep 13 08:43:59 2021
$end
$version
	Icarus Verilog
$end
$timescale
	100ps
$end
$scope module tb_SSStateMachine $end
$var wire 1 ! t_shipGRB $end
$var wire 1 " t_Ready2Go $end
$var reg 1 # t_Done $end
$var reg 1 $ t_Go $end
$var reg 1 % t_allDone $end
$var reg 1 & t_clk $end
$var reg 1 ' t_reset $end
$scope module uut $end
$var wire 1 # Done $end
$var wire 1 $ Go $end
$var wire 1 % allDone $end
$var wire 1 & clk $end
$var wire 1 ' reset $end
$var reg 1 " Ready2Go $end
$var reg 2 ( S [1:0] $end
$var reg 2 ) nS [1:0] $end
$var reg 1 ! shipGRB $end
$upscope $end
$upscope $end
$enddefinitions $end
#0
$dumpvars
b0 )
b0 (
0'
0&
0%
0$
0#
1"
0!
$end
#100
1&
#200
0&
#300
1&
#400
0&
#500
1&
#600
0&
#700
1&
#800
0&
#900
1&
#1000
0&
#1100
1&
#1200
0&
#1300
1&
#1400
0&
#1500
1&
#1600
0&
#1700
1&
#1800
0&
#1900
1&
#2000
0&
#2100
1&
#2200
0&
#2300
1&
#2400
0&
#2500
1&
#2600
0&
#2700
1&
#2800
0&
#2900
1&
#3000
0&
#3100
1&
#3200
0&
#3300
1&
#3400
0&
#3500
1&
#3600
0&
#3700
1&
#3800
0&
#3900
1&
#4000
b1 )
0&
1$
#4100
1!
0"
b1 (
1&
#4200
0&
#4300
1&
#4400
0&
#4500
1&
#4600
0&
#4700
1&
#4800
0&
#4900
1&
#5000
0&
0$
#5100
1&
#5200
0&
#5300
1&
#5400
0&
#5500
1&
#5600
0&
#5700
1&
#5800
0&
#5900
1&
#6000
0&
#6100
1&
#6200
0&
#6300
1&
#6400
0&
#6500
1&
#6600
0&
#6700
1&
#6800
0&
#6900
1&
#7000
0&
#7100
1&
#7200
0&
#7300
1&
#7400
0&
#7500
1&
#7600
0&
#7700
1&
#7800
0&
#7900
1&
#8000
0&
#8100
1&
#8200
0&
#8300
1&
#8400
0&
#8500
1&
#8600
0&
#8700
1&
#8800
0&
#8900
1&
#9000
0&
#9100
1&
#9200
0&
#9300
1&
#9400
0&
#9500
1&
#9600
0&
#9700
1&
#9800
0&
#9900
1&
#10000
0&
#10100
1&
#10200
0&
#10300
1&
#10400
0&
#10500
1&
#10600
0&
#10700
1&
#10800
0&
#10900
1&
#11000
0&
#11100
1&
#11200
0&
#11300
1&
#11400
0&
#11500
1&
#11600
0&
#11700
1&
#11800
0&
#11900
1&
#12000
0&
#12100
1&
#12200
0&
#12300
1&
#12400
0&
#12500
1&
#12600
0&
#12700
1&
#12800
0&
#12900
1&
#13000
b10 )
0&
1#
#13100
0!
b10 (
1&
#13200
0&
#13300
1&
#13400
0&
#13500
1&
#13600
0&
#13700
1&
#13800
0&
#13900
1&
#14000
0&
0#
#14100
1&
#14200
0&
#14300
1&
#14400
0&
#14500
1&
#14600
0&
#14700
1&
#14800
0&
#14900
1&
#15000
0&
#15100
1&
#15200
0&
#15300
1&
#15400
0&
#15500
1&
#15600
0&
#15700
1&
#15800
0&
#15900
1&
#16000
0&
#16100
1&
#16200
0&
#16300
1&
#16400
0&
#16500
1&
#16600
0&
#16700
1&
#16800
0&
#16900
1&
#17000
0&
#17100
1&
#17200
0&
#17300
1&
#17400
0&
#17500
1&
#17600
0&
#17700
1&
#17800
0&
#17900
1&
#18000
0&
#18100
1&
#18200
0&
#18300
1&
#18400
0&
#18500
1&
#18600
0&
#18700
1&
#18800
0&
#18900
1&
#19000
0&
#19100
1&
#19200
0&
#19300
1&
#19400
0&
#19500
1&
#19600
0&
#19700
1&
#19800
0&
#19900
1&
#20000
0&
#20100
1&
#20200
0&
#20300
1&
#20400
0&
#20500
1&
#20600
0&
#20700
1&
#20800
0&
#20900
1&
#21000
0&
#21100
1&
#21200
0&
#21300
1&
#21400
0&
#21500
1&
#21600
0&
#21700
1&
#21800
0&
#21900
1&
#22000
0&
1$
#22100
1&
#22200
0&
#22300
1&
#22400
0&
#22500
1&
#22600
0&
#22700
1&
#22800
0&
#22900
1&
#23000
0&
0$
