HW3/Problem1/BitCounter.v
module BitCounter(Count, ClearCounter, IncCounter, clk, reset);
    output [7:0] Count;
    input ClearCounter, IncCounter;
    input clk, reset;

    reg [7:0] Count, nCount;

    //assign Count = nCount;

    // Handle reset or clear counter inputs
    always @(posedge clk)
    begin
        if (reset == 1 | ClearCounter == 1)
        begin
            Count <= 0;
            nCount <= 0;
        end
        else
            Count <= nCount;
    end

    always @(posedge clk)
    begin
        if (reset == 1)
        begin
            nCount <= 0;
        end
        else
            nCount <= nCount + 1;
        
    end

endmodule

HW3/Problem1/tb_BitCounter.v
`timescale 10ns/100ps
module tb_BitCounter;
    wire [7:0] t_Count;

    reg t_ClearCounter, t_IncCounter;
    reg t_clk, t_reset;

    BitCounter uut(t_Count, t_ClearCounter, t_IncCounter, t_clk, t_reset);

    initial
    begin
        $dumpfile("tb_BbitCounter.vcd");
        $dumpvars(0, tb_BitCounter);
    end

    initial begin t_clk = 0; forever #1 t_clk = ~t_clk; end

    initial
    begin
        t_ClearCounter = 0; t_IncCounter = 0; t_reset = 0;
    end
    
    initial
    begin
        #00     begin t_reset = 1; t_ClearCounter = 0; t_IncCounter = 0; end
        #12     begin t_reset = 0; t_ClearCounter = 0; t_IncCounter = 1; end
        #12     begin t_reset = 0; t_ClearCounter = 1; t_IncCounter = 1; end
        #12     begin t_reset = 0; t_ClearCounter = 0; t_IncCounter = 1; end
        #12     begin t_reset = 1; t_ClearCounter = 0; t_IncCounter = 1; end
        #12     begin t_reset = 0; t_ClearCounter = 0; t_IncCounter = 1; end
        #12     begin t_reset = 0; t_ClearCounter = 0; t_IncCounter = 0; end
        #12     begin t_reset = 0; t_ClearCounter = 1; t_IncCounter = 0; end
        #10     $finish;
    end

endmodule

HW3/Problem1/tb_BbitCounter.vcd
$date
	Sun Sep 19 14:18:05 2021
$end
$version
	Icarus Verilog
$end
$timescale
	100ps
$end
$scope module tb_BitCounter $end
$var wire 8 ! t_Count [7:0] $end
$var reg 1 " t_ClearCounter $end
$var reg 1 # t_IncCounter $end
$var reg 1 $ t_clk $end
$var reg 1 % t_reset $end
$scope module uut $end
$var wire 1 " ClearCounter $end
$var wire 1 # IncCounter $end
$var wire 1 $ clk $end
$var wire 1 % reset $end
$var reg 8 & Count [7:0] $end
$var reg 8 ' nCount [7:0] $end
$upscope $end
$upscope $end
$enddefinitions $end
#0
$dumpvars
bx '
bx &
1%
0$
0#
0"
bx !
$end
#100
b0 !
b0 &
b0 '
1$
#200
0$
#300
1$
#400
0$
#500
1$
#600
0$
#700
1$
#800
0$
#900
1$
#1000
0$
#1100
1$
#1200
0$
1#
0%
#1300
b1 '
1$
#1400
0$
#1500
b10 '
b1 !
b1 &
1$
#1600
0$
#1700
b10 !
b10 &
b11 '
1$
#1800
0$
#1900
b100 '
b11 !
b11 &
1$
#2000
0$
#2100
b100 !
b100 &
b101 '
1$
#2200
0$
#2300
b110 '
b101 !
b101 &
1$
#2400
0$
1"
#2500
b0 !
b0 &
b0 '
1$
#2600
0$
#2700
b1 '
1$
#2800
0$
#2900
b0 '
1$
#3000
0$
#3100
b1 '
1$
#3200
0$
#3300
b0 '
1$
#3400
0$
#3500
b1 '
1$
#3600
0$
0"
#3700
b1 !
b1 &
b10 '
1$
#3800
0$
#3900
b11 '
b10 !
b10 &
1$
#4000
0$
#4100
b11 !
b11 &
b100 '
1$
#4200
0$
#4300
b101 '
b100 !
b100 &
1$
#4400
0$
#4500
b101 !
b101 &
b110 '
1$
#4600
0$
#4700
b111 '
b110 !
b110 &
1$
#4800
0$
1%
#4900
b0 !
b0 &
b0 '
1$
#5000
0$
#5100
1$
#5200
0$
#5300
1$
#5400
0$
#5500
1$
#5600
0$
#5700
1$
#5800
0$
#5900
1$
#6000
0$
0%
#6100
b1 '
1$
#6200
0$
#6300
b10 '
b1 !
b1 &
1$
#6400
0$
#6500
b10 !
b10 &
b11 '
1$
#6600
0$
#6700
b100 '
b11 !
b11 &
1$
#6800
0$
#6900
b100 !
b100 &
b101 '
1$
#7000
0$
#7100
b110 '
b101 !
b101 &
1$
#7200
0$
0#
#7300
b110 !
b110 &
b111 '
1$
#7400
0$
#7500
b1000 '
b111 !
b111 &
1$
#7600
0$
#7700
b1000 !
b1000 &
b1001 '
1$
#7800
0$
#7900
b1010 '
b1001 !
b1001 &
1$
#8000
0$
#8100
b1010 !
b1010 &
b1011 '
1$
#8200
0$
#8300
b1100 '
b1011 !
b1011 &
1$
#8400
0$
1"
#8500
b0 !
b0 &
b0 '
1$
#8600
0$
#8700
b1 '
1$
#8800
0$
#8900
b0 '
1$
#9000
0$
#9100
b1 '
1$
#9200
0$
#9300
b0 '
1$
